{
  "id": "idea_077",
  "source_file": "Reddit Stories 100+ Content Ideas for Zenlit.md",
  "category": "human_insights",
  "title": "Instacart Safety First Over Everything",
  "raw_text": "Instacart Safety First Over Everything",
  "key_points": [
    "Customer deception",
    "husband-wife dynamics",
    "driver vulnerability"
  ],
  "href": "https://www.reddit.com/r/InstacartShoppers/comments/1iuihnx/ladies_safety_first_over_everything/",
  "metadata": {
    "engagement": "Safety priority message",
    "source_type": "reddit",
    "subreddit": "r/InstacartShoppers",
    "appeal": "Customer deception, husband-wife dynamics, driver vulnerability",
    "content_angle": "Why female gig workers must prioritize safety over earnings"
  },
  "extracted_date": "2025-10-24"
}